pymodo/__init__.py
pymodo/__main__.py
pymodo/_version.py
pymodo/modo.py
pymodo/bin/.gitignore
pymodo/bin/modo_linux
pymodo/bin/modo_macos
pymodo/bin/modo_win.exe
pymodo-0.11.12.dist-info/licenses/LICENSE
pymodo-0.11.12.dist-info/METADATA
pymodo-0.11.12.dist-info/WHEEL
pymodo-0.11.12.dist-info/entry_points.txt
pymodo-0.11.12.dist-info/top_level.txt
pymodo-0.11.12.dist-info/RECORD
