Metadata-Version: 2.4
Name: pymodo
Version: 0.11.12
Summary: Python wrapper for Modo, a documentation generator (DocGen) for the Mojo programming language.
Author-email: Martin Lange <martin_lange_@gmx.net>
Project-URL: Homepage, https://github.com/mlange-42/modo
Project-URL: Issues, https://github.com/mlange-42/modo/issues
Classifier: Programming Language :: Python :: 3
Classifier: Operating System :: OS Independent
Requires-Python: >=3.8
License-File: LICENSE
Dynamic: license-file
